{
  "info": {
    "name": "MERN Stack Boilerplate API",
    "description": "Complete API collection for MERN Stack Boilerplate",
    "schema": "https://schema.getpostman.com/json/collection/v2.1.0/collection.json"
  },
  "variable": [
    {
      "key": "baseUrl",
      "value": "http://localhost:5000/api",
      "type": "string"
    },
    {
      "key": "token",
      "value": "",
      "type": "string"
    }
  ],
  "item": [
    {
      "name": "Health",
      "item": [
        {
          "name": "Health Check",
          "request": {
            "method": "GET",
            "header": [],
            "url": {
              "raw": "{{baseUrl}}/health",
              "host": ["{{baseUrl}}"],
              "path": ["health"]
            }
          }
        }
      ]
    },
    {
      "name": "Authentication",
      "item": [
        {
          "name": "Register User",
          "event": [
            {
              "listen": "test",
              "script": {
                "exec": [
                  "if (pm.response.code === 201) {",
                  "    const response = pm.response.json();",
                  "    pm.environment.set('token', response.token);",
                  "}"
                ]
              }
            }
          ],
          "request": {
            "method": "POST",
            "header": [
              {
                "key": "Content-Type",
                "value": "application/json"
              }
            ],
            "body": {
              "mode": "raw",
              "raw": "{\n  \"name\": \"Test User\",\n  \"email\": \"test@example.com\",\n  \"password\": \"password123\"\n}"
            },
            "url": {
              "raw": "{{baseUrl}}/auth/register",
              "host": ["{{baseUrl}}"],
              "path": ["auth", "register"]
            }
          }
        },
        {
          "name": "Login User",
          "event": [
            {
              "listen": "test",
              "script": {
                "exec": [
                  "if (pm.response.code === 200) {",
                  "    const response = pm.response.json();",
                  "    pm.environment.set('token', response.token);",
                  "}"
                ]
              }
            }
          ],
          "request": {
            "method": "POST",
            "header": [
              {
                "key": "Content-Type",
                "value": "application/json"
              }
            ],
            "body": {
              "mode": "raw",
              "raw": "{\n  \"email\": \"test@example.com\",\n  \"password\": \"password123\"\n}"
            },
            "url": {
              "raw": "{{baseUrl}}/auth/login",
              "host": ["{{baseUrl}}"],
              "path": ["auth", "login"]
            }
          }
        },
        {
          "name": "Get Current User",
          "request": {
            "method": "GET",
            "header": [
              {
                "key": "Authorization",
                "value": "Bearer {{token}}"
              }
            ],
            "url": {
              "raw": "{{baseUrl}}/auth/me",
              "host": ["{{baseUrl}}"],
              "path": ["auth", "me"]
            }
          }
        },
        {
          "name": "Update User Details",
          "request": {
            "method": "PUT",
            "header": [
              {
                "key": "Authorization",
                "value": "Bearer {{token}}"
              },
              {
                "key": "Content-Type",
                "value": "application/json"
              }
            ],
            "body": {
              "mode": "raw",
              "raw": "{\n  \"name\": \"Updated Name\",\n  \"email\": \"updated@example.com\"\n}"
            },
            "url": {
              "raw": "{{baseUrl}}/auth/updatedetails",
              "host": ["{{baseUrl}}"],
              "path": ["auth", "updatedetails"]
            }
          }
        },
        {
          "name": "Update Password",
          "request": {
            "method": "PUT",
            "header": [
              {
                "key": "Authorization",
                "value": "Bearer {{token}}"
              },
              {
                "key": "Content-Type",
                "value": "application/json"
              }
            ],
            "body": {
              "mode": "raw",
              "raw": "{\n  \"currentPassword\": \"password123\",\n  \"newPassword\": \"newpassword123\"\n}"
            },
            "url": {
              "raw": "{{baseUrl}}/auth/updatepassword",
              "host": ["{{baseUrl}}"],
              "path": ["auth", "updatepassword"]
            }
          }
        },
        {
          "name": "Logout",
          "request": {
            "method": "GET",
            "header": [
              {
                "key": "Authorization",
                "value": "Bearer {{token}}"
              }
            ],
            "url": {
              "raw": "{{baseUrl}}/auth/logout",
              "host": ["{{baseUrl}}"],
              "path": ["auth", "logout"]
            }
          }
        }
      ]
    },
    {
      "name": "Users",
      "item": [
        {
          "name": "Get My Profile",
          "request": {
            "method": "GET",
            "header": [
              {
                "key": "Authorization",
                "value": "Bearer {{token}}"
              }
            ],
            "url": {
              "raw": "{{baseUrl}}/users/me",
              "host": ["{{baseUrl}}"],
              "path": ["users", "me"]
            }
          }
        },
        {
          "name": "Get All Users (Admin)",
          "request": {
            "method": "GET",
            "header": [
              {
                "key": "Authorization",
                "value": "Bearer {{token}}"
              }
            ],
            "url": {
              "raw": "{{baseUrl}}/users",
              "host": ["{{baseUrl}}"],
              "path": ["users"]
            }
          }
        },
        {
          "name": "Get Single User (Admin)",
          "request": {
            "method": "GET",
            "header": [
              {
                "key": "Authorization",
                "value": "Bearer {{token}}"
              }
            ],
            "url": {
              "raw": "{{baseUrl}}/users/:id",
              "host": ["{{baseUrl}}"],
              "path": ["users", ":id"]
            }
          }
        },
        {
          "name": "Create User (Admin)",
          "request": {
            "method": "POST",
            "header": [
              {
                "key": "Authorization",
                "value": "Bearer {{token}}"
              },
              {
                "key": "Content-Type",
                "value": "application/json"
              }
            ],
            "body": {
              "mode": "raw",
              "raw": "{\n  \"name\": \"Admin User\",\n  \"email\": \"admin@example.com\",\n  \"password\": \"password123\",\n  \"role\": \"admin\"\n}"
            },
            "url": {
              "raw": "{{baseUrl}}/users",
              "host": ["{{baseUrl}}"],
              "path": ["users"]
            }
          }
        },
        {
          "name": "Update User (Admin)",
          "request": {
            "method": "PUT",
            "header": [
              {
                "key": "Authorization",
                "value": "Bearer {{token}}"
              },
              {
                "key": "Content-Type",
                "value": "application/json"
              }
            ],
            "body": {
              "mode": "raw",
              "raw": "{\n  \"name\": \"Updated Admin\",\n  \"role\": \"admin\"\n}"
            },
            "url": {
              "raw": "{{baseUrl}}/users/:id",
              "host": ["{{baseUrl}}"],
              "path": ["users", ":id"]
            }
          }
        },
        {
          "name": "Delete User (Admin)",
          "request": {
            "method": "DELETE",
            "header": [
              {
                "key": "Authorization",
                "value": "Bearer {{token}}"
              }
            ],
            "url": {
              "raw": "{{baseUrl}}/users/:id",
              "host": ["{{baseUrl}}"],
              "path": ["users", ":id"]
            }
          }
        }
      ]
    }
  ]
}